isodate/__init__.py
isodate/duration.py
isodate/isodates.py
isodate/isodatetime.py
isodate/isoduration.py
isodate/isoerror.py
isodate/isostrf.py
isodate/isotime.py
isodate/isotzinfo.py
isodate/tzinfo.py
isodate2-0.9.0.dist-info/LICENSE.md
isodate2-0.9.0.dist-info/METADATA
isodate2-0.9.0.dist-info/WHEEL
isodate2-0.9.0.dist-info/top_level.txt
isodate2-0.9.0.dist-info/RECORD
